alibabacloud_hcs_mgw20171024/__init__.py
alibabacloud_hcs_mgw20171024/client.py
alibabacloud_hcs_mgw20171024/models.py
alibabacloud_hcs_mgw20171024-1.0.0.dist-info/LICENSE
alibabacloud_hcs_mgw20171024-1.0.0.dist-info/METADATA
alibabacloud_hcs_mgw20171024-1.0.0.dist-info/WHEEL
alibabacloud_hcs_mgw20171024-1.0.0.dist-info/top_level.txt
alibabacloud_hcs_mgw20171024-1.0.0.dist-info/RECORD
